csvlite/__init__.py
csvlite/__main__.py
csvlite/py.typed
csvlite-0.1.0.dist-info/entry_points.txt
csvlite-0.1.0.dist-info/LICENSE
csvlite-0.1.0.dist-info/WHEEL
csvlite-0.1.0.dist-info/METADATA
csvlite-0.1.0.dist-info/RECORD
