Metadata-Version: 2.1
Name: csvlite
Version: 0.1.0
Summary: CSVLite
Home-page: https://github.com/lukemiloszewski/csvlite
License: MIT
Author: Luke Miloszewski
Author-email: lukemiloszewski@gmail.com
Requires-Python: >=3.8.0,<3.10.0
Classifier: License :: OSI Approved :: MIT License
Classifier: Programming Language :: Python :: 3
Classifier: Programming Language :: Python :: 3.8
Classifier: Programming Language :: Python :: 3.9
Requires-Dist: typer (>=0.4.0,<0.5.0)
Project-URL: Repository, https://github.com/lukemiloszewski/csvlite
